webtoolkitex/__init__.py
webtoolkitex/crawlers/__init__.py
webtoolkitex/crawlers/curlcffi.py
webtoolkitex/crawlers/httpmorph.py
webtoolkitex/crawlers/httpx.py
webtoolkitex/crawlers/stealth.py
webtoolkitex/crawlers/ytdlp.py
webtoolkitex/entryrules.py
webtoolkitex/handlers/__init__.py
webtoolkitex/handlers/handlerchannelyoutube.py
webtoolkitex/handlers/handlervideoyoutube.py
webtoolkitex/urlex.py
webtoolkitex/utils/__init__.py
webtoolkitex/utils/basictypes.py
webtoolkitex/utils/dateutils.py
webtoolkitex/utils/logger.py
webtoolkitex/utils/programwrappers/__init__.py
webtoolkitex/utils/programwrappers/ffmpeg.py
webtoolkitex/utils/programwrappers/id3v2.py
webtoolkitex/utils/programwrappers/vlc.py
webtoolkitex/utils/programwrappers/wget.py
webtoolkitex/utils/programwrappers/ytdlp.py
webtoolkitex/utils/programwrappers/ytdownloader.py
webtoolkitex/utils/serializers/__init__.py
webtoolkitex/utils/serializers/jsonimporter.py
webtoolkitex/utils/serializers/youtubelinkjson.py
webtoolkitex/webconfig.py
webtoolkitex-0.0.24.dist-info/LICENSE
webtoolkitex-0.0.24.dist-info/METADATA
webtoolkitex-0.0.24.dist-info/WHEEL
webtoolkitex-0.0.24.dist-info/RECORD
