Metadata-Version: 2.1
Name: webtoolkitex
Version: 0.0.24
Summary: Web tools and interfaces for Internet data processing.
License: GPL3
Author: Iwan Grozny
Author-email: renegat@renegat0x0.ddns.net
Requires-Python: >=3.10,<4.0
Classifier: License :: Other/Proprietary License
Classifier: Programming Language :: Python :: 3
Classifier: Programming Language :: Python :: 3.10
Classifier: Programming Language :: Python :: 3.11
Classifier: Programming Language :: Python :: 3.12
Requires-Dist: beautifulsoup4 (>=4.13.5,<5.0.0)
Requires-Dist: brutefeedparser (>=0.10.5,<0.11.0)
Requires-Dist: curl-cffi (>=0.14.0,<0.15.0)
Requires-Dist: flask
Requires-Dist: httpmorph
Requires-Dist: lxml (>=5.3.0,<6.0.0)
Requires-Dist: psutil
Requires-Dist: python-dateutil (>=2.8.2,<3.0.0)
Requires-Dist: pytz (>=2024.2,<2025.0)
Requires-Dist: stealth-requests (>=2.0.4,<3.0.0)
Requires-Dist: url-cleaner
Requires-Dist: webtoolkit (>=0.0.191,<0.0.192)
Requires-Dist: yt-dlp (>=2025.10.22,<2026.0.0)
